LICENSE.APACHE
LICENSE.BSD
MANIFEST.in
README.md
setup.py
/var/folders/pb/jv_m_p714_qgdvmkvgfqns0w0000gn/T/tmp5_dem980/fastpbkdf2-1.0.0/fastpbkdf2.c
/var/folders/pb/jv_m_p714_qgdvmkvgfqns0w0000gn/T/tmp6uxrm_mz/fastpbkdf2-1.0.0/fastpbkdf2.c
src/build_fastpbkdf2.py
src/fastpbkdf2.tar.gz
src/fastpbkdf2/__init__.py
src/fastpbkdf2.egg-info/PKG-INFO
src/fastpbkdf2.egg-info/SOURCES.txt
src/fastpbkdf2.egg-info/dependency_links.txt
src/fastpbkdf2.egg-info/not-zip-safe
src/fastpbkdf2.egg-info/requires.txt
src/fastpbkdf2.egg-info/top_level.txt