Metadata-Version: 1.1
Name: fastpbkdf2
Version: 0.2
Summary: A faster implementation of PBKDF2
Home-page: https://github.com/Ayrx/python-fastpbkdf2
Author: Terry Chia
Author-email: terrycwk1994@gmail.com
License: BSD or Apache License, Version 2.0
Platform: UNKNOWN
Classifier: Programming Language :: Python :: Implementation :: CPython
Classifier: Programming Language :: Python :: Implementation :: PyPy
Classifier: Programming Language :: Python :: 2
Classifier: Programming Language :: Python :: 2.7
Classifier: Programming Language :: Python :: 3
Classifier: Programming Language :: Python :: 3.3
Classifier: Programming Language :: Python :: 3.4
Classifier: Programming Language :: Python :: 3.5
Classifier: Programming Language :: Python :: 3.6
Classifier: Topic :: Security :: Cryptography
